monitoring_plugins/CHANGELOG.md
monitoring_plugins/CONTRIBUTORS.md
monitoring_plugins/LICENSE
monitoring_plugins/README.md
monitoring_plugins/__init__.py
monitoring_plugins/check_ciphers.py
monitoring_plugins/check_deny_tls_version.sh
monitoring_plugins/check_dnssec_status.py
monitoring_plugins/check_docker_login.sh
monitoring_plugins/check_existing_users.py
monitoring_plugins/check_group_members.py
monitoring_plugins/check_open_ports.py
monitoring_plugins/check_page_content.py
monitoring_plugins/check_path_exists.sh
monitoring_plugins/check_reboot_required.py
monitoring_plugins/check_sensor_DS18B20.py
monitoring_plugins/check_spf.py
monitoring_plugins/check_sshd_security.py
monitoring_plugins/check_ufw_status.py
monitoring_plugins/snmp/__init__.py
monitoring_plugins/snmp/PowerNet_MIB/__init__.py
monitoring_plugins/snmp/PowerNet_MIB/check_battery_bad_battery_packs.py
monitoring_plugins/snmp/PowerNet_MIB/check_battery_capacity.py
monitoring_plugins/snmp/PowerNet_MIB/check_battery_packs_attached.py
monitoring_plugins/snmp/PowerNet_MIB/check_battery_remaining_runtime.py
monitoring_plugins/snmp/PowerNet_MIB/check_battery_replacement.py
monitoring_plugins/snmp/PowerNet_MIB/check_battery_status.py
monitoring_plugins/snmp/PowerNet_MIB/check_battery_temperature.py
monitoring_plugins/snmp/PowerNet_MIB/check_diagnostic_test_result.py
monitoring_plugins/snmp/PowerNet_MIB/check_last_diagnostic_test_result_time.py
monitoring_plugins/snmp/Synology/__init__.py
monitoring_plugins/snmp/Synology/check_cpu_fan_status.py
monitoring_plugins/snmp/Synology/check_disk_temperature.py
monitoring_plugins/snmp/Synology/check_gpu_info.py
monitoring_plugins/snmp/Synology/check_power_status.py
monitoring_plugins/snmp/Synology/check_raid_status.py
monitoring_plugins/snmp/Synology/check_service_running.py
monitoring_plugins/snmp/Synology/check_service_used.py
monitoring_plugins/snmp/Synology/check_smart.py
monitoring_plugins/snmp/Synology/check_space_io.py
monitoring_plugins-2.2.0.post2.dist-info/LICENSE
monitoring_plugins-2.2.0.post2.dist-info/METADATA
monitoring_plugins-2.2.0.post2.dist-info/WHEEL
monitoring_plugins-2.2.0.post2.dist-info/top_level.txt
monitoring_plugins-2.2.0.post2.dist-info/RECORD
