Metadata-Version: 2.1
Name: monitoring-plugins
Version: 2.2.0.post2
Summary: Plugins for monitoring
Home-page: https://github.com/f-froehlich/monitoring-plugins
Author: Fabian Fröhlich
Author-email: mail@confgen.org
License: AGPLv3
Download-URL: https://pypi.org/project/monitoring-plugins/
Keywords: icinga,icinga2,icinga2-plugin,monitoring,check,nagios,nagios-plugin,nrpe,healthcheck,serverstatus,security,security-tools
Platform: UNKNOWN
Requires-Dist: monitoring-utils (~=2.1)
